AUTHORS
CHANGES
LICENSE
MANIFEST.in
README
TODO
setup.py
docs/Makefile
docs/conf.py
docs/index.rst
docs/make.bat
docs/news.rst
docs/pkg.rst
docs/pypi.rst
docs/_themes/rtd/theme.conf
docs/_themes/rtd/static/rtd.css_t
pkgtools/__init__.py
pkgtools/pkg.py
pkgtools/pypi.py
pkgtools/utils.py
pkgtools.egg-info/PKG-INFO
pkgtools.egg-info/SOURCES.txt
pkgtools.egg-info/dependency_links.txt
pkgtools.egg-info/top_level.txt
pkgtools/__pycache__/__init__.cpython-33.pyc
pkgtools/__pycache__/pypi.cpython-33.pyc
pkgtools/__pycache__/utils.cpython-33.pyc