Metadata-Version: 1.1
Name: pkgtools
Version: 0.7.3
Summary: Python Packages Tools, with Python 3.3 support
Home-page: http://pkgtools.readthedocs.org/
Author: Michele Lacchia
Author-email: <michelelacchia@gmail.com>
License: MIT
Download-URL: http://pypi.python.org/pypi/pkgtools
Keywords: python,packages,pypi,setuptools,distutils
Platform: any
